{"inkVersion":21,"root":[[["done",{"#f":5,"#n":"g-0"}],null],"done",{"top_knot":[["^There are two wolves inside of you.","\n","^Which do you choose?","\n","ev","str","^Uh, that one?","/str","/ev",{"*":".^.c-0","flg":20},"ev","str","^The one over there, I guess.","/str","/ev",{"*":".^.c-1","flg":20},{"c-0":["^ ","#","^make red","/#","\n","^Fine, that dude.","\n","^Good choice!","\n",{"->":"ending"},{"#f":5}],"c-1":["^ ","#","^make blue","/#","\n","^Him it is.","\n","^Awful fucking choice, my dude","\n",{"->":"ending"},{"#f":5}]}],{"#f":1}],"ending":[[["^They lived happily ever after.","\n","end",{"#f":5,"#n":"g-0"}],null],{"#f":1}],"#f":1}],"listDefs":{}}